lane4text/__init__.py
lane4text/download.py
lane4text/lane_trainer.py
lane4text/loss.py
lane4text/option.py
lane4text/process.py
lane4text/train.py
lane4text/trainer.py
lane4text/word.py
lane4text/general_model/__init__.py
lane4text/general_model/core.py
lane4text/general_model/test.py
lane4text/trainer/__init__.py
lane4text/trainer/base_trainer.py
lane4text/trainer/co_trainer.py
lane4text/trainer/divide_mix_trainer.py
lane4text/trainer/gsmc_trainer.py
lane4text/trainer/me_trainer.py
lane4text-0.1.3.dist-info/METADATA
lane4text-0.1.3.dist-info/WHEEL
lane4text-0.1.3.dist-info/top_level.txt
lane4text-0.1.3.dist-info/RECORD
