Metadata-Version: 2.2
Name: lane4text
Version: 0.1.3
Summary: 带噪文本分类
Author: huangyongqi
Classifier: Programming Language :: Python :: 3
Classifier: License :: OSI Approved :: MIT License
Dynamic: author
Dynamic: classifier
Dynamic: description-content-type
Dynamic: summary
